rtl/alu_defs.vh
// Arithmetic operations
`define OP_ADD 4'b0000
`define OP_SUB 4'b0001
`define OP_INC 4'b0010
`define OP_DEC 4'b0011

// Logical operations
`define OP_AND 4'b0100
`define OP_OR  4'b0101
`define OP_XOR 4'b0110
`define OP_NOT 4'b0111

// Shift operations
`define OP_SLL 4'b1000
`define OP_SRL 4'b1001

rtl/alu_shift.v
`include "alu_defs.vh"

module alu_shift(
    input  [7:0] A,
    input  [3:0] opcode,

    output reg [7:0] result,
    output reg zero,
    output reg negative
);

    always @(*) begin

        // Default value
        result = 8'b0;

        case(opcode)

            // Logical shift left 
            `OP_SLL: result = A << 1;

            // Logical shift right 
            `OP_SRL: result = A >> 1;

            default: result = 8'b0;

        endcase

        // Flags
        zero = (result == 8'b0);
        negative = result[7];

    end

endmodule

rtl/alu_logic.v
`include "alu_defs.vh"

module alu_logic(
    input  [7:0] A,
    input  [7:0] B,
    input  [3:0] opcode,

    output reg [7:0] result,
    output reg zero,
    output reg negative
);

    always @(*) begin

        // Default value
        result = 8'b0;

        case(opcode)

            `OP_AND: result = A & B;

            `OP_OR:  result = A | B;

            `OP_XOR: result = A ^ B;

            `OP_NOT: result = ~A;

            default: result = 8'b0;

        endcase

        // Flags
        zero = (result == 8'b0);
        negative = result[7];

    end

endmodule

rtl/alu_arith.v
`include "alu_defs.vh"

module alu_arith(
    input  [7:0] A,
    input  [7:0] B,
    input  [3:0] opcode,

    output reg [7:0] result,
    output reg carry_out,
    output reg overflow,
    output reg zero,
    output reg negative
);

    reg [8:0] temp;   
    // 9 bits to store carry

    always @(*) begin

        // Default values
        temp = 9'b0;
        result = 8'b0;
        carry_out = 0;
        overflow = 0;

        case(opcode)

            // Addition
            `OP_ADD: begin
                temp = A + B;
                result = temp[7:0];
                carry_out = temp[8];

                overflow = (~A[7] & ~B[7] & result[7]) |
                           ( A[7] &  B[7] & ~result[7]);
            end

            // Subtraction
            `OP_SUB: begin
                temp = A - B;
                result = temp[7:0];
                carry_out = temp[8];

                overflow = (~A[7] & B[7] & result[7]) |
                           (A[7] & ~B[7] & ~result[7]);
            end

            // Increment
            `OP_INC: begin
                temp = A + 1;
                result = temp[7:0];
                carry_out = temp[8];
            end

            // Decrement
            `OP_DEC: begin
                temp = A - 1;
                result = temp[7:0];
                carry_out = temp[8];
            end

            default: begin
                result = 8'b0;
            end

        endcase

        // Flags
        zero = (result == 8'b0);
        negative = result[7];

    end

endmodule

rtl/alu_top.v
`include "alu_defs.vh"

module alu_top(
    input  [7:0] A,
    input  [7:0] B,
    input  [3:0] opcode,

    output reg [7:0] result,
    output reg carry_out,
    output reg overflow,
    output reg zero,
    output reg negative
);

    // Outputs from submodules
    wire [7:0] arith_result;
    wire       arith_carry;
    wire       arith_overflow;
    wire       arith_zero;
    wire       arith_negative;

    wire [7:0] logic_result;
    wire       logic_zero;
    wire       logic_negative;

    wire [7:0] shift_result;
    wire       shift_zero;
    wire       shift_negative;

    // Instantiation

    alu_arith u_arith (
        .A(A),
        .B(B),
        .opcode(opcode),
        .result(arith_result),
        .carry_out(arith_carry),
        .overflow(arith_overflow),
        .zero(arith_zero),
        .negative(arith_negative)
    );

    alu_logic u_logic (
        .A(A),
        .B(B),
        .opcode(opcode),
        .result(logic_result),
        .zero(logic_zero),
        .negative(logic_negative)
    );

    alu_shift u_shift (
        .A(A),
        .opcode(opcode),
        .result(shift_result),
        .zero(shift_zero),
        .negative(shift_negative)
    );

    // Output (Mux) 

    always @(*) begin

        // Default
        result     = 8'b0;
        carry_out  = 0;
        overflow   = 0;
        zero       = 0;
        negative   = 0;

        case(opcode)

            // Arithmetic
            `OP_ADD,
            `OP_SUB,
            `OP_INC,
            `OP_DEC: begin
                result     = arith_result;
                carry_out  = arith_carry;
                overflow   = arith_overflow;
                zero       = arith_zero;
                negative   = arith_negative;
            end

            // Logical
            `OP_AND,
            `OP_OR,
            `OP_XOR,
            `OP_NOT: begin
                result     = logic_result;
                zero       = logic_zero;
                negative   = logic_negative;
            end

            // Shift
            `OP_SLL,
            `OP_SRL: begin
                result     = shift_result;
                zero       = shift_zero;
                negative   = shift_negative;
            end

            default: begin
                result = 8'b0;
            end

        endcase
    end

endmodule

tb/alu_ref_model.v
`include "alu_defs.vh"

module alu_ref_model(
    input  [7:0] A,
    input  [7:0] B,
    input  [3:0] opcode,

    output reg [7:0] result,
    output reg carry_out,
    output reg overflow,
    output reg zero,
    output reg negative
);

    reg [8:0] temp;

    always @(*) begin

        // Default values
        temp = 9'd0;
        result = 8'd0;
        carry_out = 0;
        overflow = 0;

        case(opcode)

            // Arithmetic
            `OP_ADD: begin
                temp = A + B;
                result = temp[7:0];
                carry_out = temp[8];

                overflow = (~A[7] & ~B[7] & result[7]) |
                           ( A[7] &  B[7] & ~result[7]);
            end

            `OP_SUB: begin
                temp = A - B;
                result = temp[7:0];
                carry_out = temp[8];

                overflow = (~A[7] & B[7] & result[7]) |
                           ( A[7] & ~B[7] & ~result[7]);
            end

            `OP_INC: begin
                temp = A + 1;
                result = temp[7:0];
                carry_out = temp[8];
            end

            `OP_DEC: begin
                temp = A - 1;
                result = temp[7:0];
                carry_out = temp[8];
            end

            // Logical
            `OP_AND: result = A & B;
            `OP_OR:  result = A | B;
            `OP_XOR: result = A ^ B;
            `OP_NOT: result = ~A;

            // Shift
            `OP_SLL: result = A << 1;
            `OP_SRL: result = A >> 1;

            default: result = 8'd0;

        endcase

        // Flags
        zero = (result == 8'd0);
        negative = result[7];

    end

endmodule

tb/alu_tb.v
`include "alu_defs.vh"

module alu_tb;

    reg [7:0] A, B;
    reg [3:0] opcode;

    wire [7:0] result;
    wire carry_out, overflow, zero, negative;
    wire [7:0] ref_result;
    wire ref_carry, ref_overflow, ref_zero, ref_negative;

    alu_ref_model ref (
        .A(A),
        .B(B),
        .opcode(opcode),
        .result(ref_result),
        .carry_out(ref_carry),
        .overflow(ref_overflow),
        .zero(ref_zero),
        .negative(ref_negative)
    );
    // DUT
    alu_top uut (
        .A(A),
        .B(B),
        .opcode(opcode),
        .result(result),
        .carry_out(carry_out),
        .overflow(overflow),
        .zero(zero),
        .negative(negative)
    );

    // Waveform
    initial begin
        $dumpfile("dump.vcd");
        $dumpvars(0, alu_tb);
    end

    // Testing Task
    task test;
    input [7:0] a_in, b_in;
    input [3:0] op_in;
    begin
        A = a_in;
        B = b_in;
        opcode = op_in;
        #10;

        if (result !== ref_result ||
            carry_out !== ref_carry ||
            overflow !== ref_overflow ||
            zero !== ref_zero ||
            negative !== ref_negative) begin

            $display("Did not Match with Golden Reference: A=%d B=%d OP=%b | DUT=%d REF=%d | C=%b/%b V=%b/%b",
          A, B, opcode,
          result, ref_result,
          carry_out, ref_carry,
          overflow, ref_overflow);

        end 
        else begin
            $display("Matched with Golden Reference: A=%d B=%d OP=%b | RESULT=%d",
                      A, B, opcode, result);
        end
        end
    endtask

    initial begin

        // Arithmetic
        test(8'd10, 8'd5, `OP_ADD);
        test(8'd10, 8'd5, `OP_SUB);
        test(8'd255, 8'd1, `OP_ADD);   // carry case
        test(8'd0, 8'd1, `OP_SUB);     // underflow
        test(8'd127, 8'd1, `OP_ADD);   // overflow
        test(8'd128, 8'd1, `OP_SUB);   // overflow

        // Logical
        test(8'b10101010, 8'b11001100, `OP_AND);
        test(8'b10101010, 8'b11001100, `OP_OR);
        test(8'b10101010, 8'b11001100, `OP_XOR);
        test(8'b10101010, 8'b00000000, `OP_NOT);

        // Shift
        test(8'b00001111, 0, `OP_SLL);
        test(8'b00001111, 0, `OP_SRL);

        // Increment or Decrement
        test(8'd10, 0, `OP_INC);
        test(8'd10, 0, `OP_DEC);

        repeat (50) begin
        test($random, $random, ($random % 10 + 10) % 10);
        end
        #20;
        $finish;

    end

endmodule

dump.vcd
$date
	Sun May 03 16:37:29 2026
$end
$version
	Icarus Verilog
$end
$timescale
	1s
$end
$scope module alu_tb $end
$var wire 1 ! zero $end
$var wire 8 " result [7:0] $end
$var wire 1 # ref_zero $end
$var wire 8 $ ref_result [7:0] $end
$var wire 1 % ref_overflow $end
$var wire 1 & ref_negative $end
$var wire 1 ' ref_carry $end
$var wire 1 ( overflow $end
$var wire 1 ) negative $end
$var wire 1 * carry_out $end
$var reg 8 + A [7:0] $end
$var reg 8 , B [7:0] $end
$var reg 4 - opcode [3:0] $end
$scope module ref $end
$var wire 8 . A [7:0] $end
$var wire 8 / B [7:0] $end
$var wire 4 0 opcode [3:0] $end
$var reg 1 ' carry_out $end
$var reg 1 & negative $end
$var reg 1 % overflow $end
$var reg 8 1 result [7:0] $end
$var reg 9 2 temp [8:0] $end
$var reg 1 # zero $end
$upscope $end
$scope module uut $end
$var wire 8 3 A [7:0] $end
$var wire 8 4 B [7:0] $end
$var wire 4 5 opcode [3:0] $end
$var wire 1 6 shift_zero $end
$var wire 8 7 shift_result [7:0] $end
$var wire 1 8 shift_negative $end
$var wire 1 9 logic_zero $end
$var wire 8 : logic_result [7:0] $end
$var wire 1 ; logic_negative $end
$var wire 1 < arith_zero $end
$var wire 8 = arith_result [7:0] $end
$var wire 1 > arith_overflow $end
$var wire 1 ? arith_negative $end
$var wire 1 @ arith_carry $end
$var reg 1 * carry_out $end
$var reg 1 ) negative $end
$var reg 1 ( overflow $end
$var reg 8 A result [7:0] $end
$var reg 1 ! zero $end
$scope module u_arith $end
$var wire 8 B A [7:0] $end
$var wire 8 C B [7:0] $end
$var wire 4 D opcode [3:0] $end
$var reg 1 @ carry_out $end
$var reg 1 ? negative $end
$var reg 1 > overflow $end
$var reg 8 E result [7:0] $end
$var reg 9 F temp [8:0] $end
$var reg 1 < zero $end
$upscope $end
$scope module u_logic $end
$var wire 8 G A [7:0] $end
$var wire 8 H B [7:0] $end
$var wire 4 I opcode [3:0] $end
$var reg 1 ; negative $end
$var reg 8 J result [7:0] $end
$var reg 1 9 zero $end
$upscope $end
$scope module u_shift $end
$var wire 8 K A [7:0] $end
$var wire 4 L opcode [3:0] $end
$var reg 1 8 negative $end
$var reg 8 M result [7:0] $end
$var reg 1 6 zero $end
$upscope $end
$upscope $end
$scope task test $end
$var reg 8 N a_in [7:0] $end
$var reg 8 O b_in [7:0] $end
$var reg 4 P op_in [3:0] $end
$upscope $end
$upscope $end
$enddefinitions $end
$comment Show the parameter values. $end
$dumpall
$end
#0
$dumpvars
b0 P
b101 O
b1010 N
b0 M
b0 L
b1010 K
b0 J
b0 I
b101 H
b1010 G
b1111 F
b1111 E
b0 D
b101 C
b1010 B
b1111 A
0@
0?
0>
b1111 =
0<
0;
b0 :
19
08
b0 7
16
b0 5
b101 4
b1010 3
b1111 2
b1111 1
b0 0
b101 /
b1010 .
b0 -
b101 ,
b1010 +
0*
0)
0(
0'
0&
0%
b1111 $
0#
b1111 "
0!
$end
#10
b101 $
b101 1
b101 2
b101 "
b101 A
b101 =
b101 E
b101 F
b1 -
b1 0
b1 5
b1 D
b1 I
b1 L
b1 P
#20
1!
1*
b0 "
b0 A
1#
1'
b0 $
b0 1
b100000000 2
1<
1@
b0 =
b0 E
b100000000 F
b0 -
b0 0
b0 5
b0 D
b0 I
b0 L
b1 ,
b1 /
b1 4
b1 C
b1 H
b11111111 +
b11111111 .
b11111111 3
b11111111 B
b11111111 G
b11111111 K
b0 P
b1 O
b11111111 N
#30
1)
b11111111 "
b11111111 A
0!
1*
1&
0#
b11111111 $
b11111111 1
1'
b111111111 2
1?
0<
b11111111 =
b11111111 E
1@
b111111111 F
b1 -
b1 0
b1 5
b1 D
b1 I
b1 L
b0 +
b0 .
b0 3
b0 B
b0 G
b0 K
b1 P
b0 N
#40
1(
1)
0*
b10000000 "
b10000000 A
1%
0'
b10000000 $
b10000000 1
b10000000 2
1>
0@
b10000000 =
b10000000 E
b10000000 F
b0 -
b0 0
b0 5
b0 D
b0 I
b0 L
b1111111 +
b1111111 .
b1111111 3
b1111111 B
b1111111 G
b1111111 K
b0 P
b1111111 N
#50
0)
1(
b1111111 "
b1111111 A
0&
1%
b1111111 $
b1111111 1
b1111111 2
0?
1>
b1111111 =
b1111111 E
b1111111 F
b1 -
b1 0
b1 5
b1 D
b1 I
b1 L
b10000000 +
b10000000 .
b10000000 3
b10000000 B
b10000000 G
b10000000 K
b1 P
b10000000 N
#60
1)
0(
b10001000 "
b10001000 A
1&
0%
b10001000 $
b10001000 1
b0 2
1<
0>
b0 =
b0 E
b0 F
1;
09
b10001000 :
b10001000 J
b100 -
b100 0
b100 5
b100 D
b100 I
b100 L
b11001100 ,
b11001100 /
b11001100 4
b11001100 C
b11001100 H
b10101010 +
b10101010 .
b10101010 3
b10101010 B
b10101010 G
b10101010 K
b100 P
b11001100 O
b10101010 N
#70
b11101110 $
b11101110 1
1)
b11101110 "
b11101110 A
b11101110 :
b11101110 J
b101 -
b101 0
b101 5
b101 D
b101 I
b101 L
b101 P
#80
0&
b1100110 $
b1100110 1
0)
b1100110 "
b1100110 A
0;
b1100110 :
b1100110 J
b110 -
b110 0
b110 5
b110 D
b110 I
b110 L
b110 P
#90
b1010101 "
b1010101 A
b1010101 $
b1010101 1
b1010101 :
b1010101 J
b111 -
b111 0
b111 5
b111 D
b111 I
b111 L
b0 ,
b0 /
b0 4
b0 C
b0 H
b111 P
b0 O
#100
b11110 "
b11110 A
b11110 $
b11110 1
19
b0 :
b0 J
06
b11110 7
b11110 M
b1000 -
b1000 0
b1000 5
b1000 D
b1000 I
b1000 L
b1111 +
b1111 .
b1111 3
b1111 B
b1111 G
b1111 K
b1000 P
b1111 N
#110
b111 $
b111 1
b111 "
b111 A
b111 7
b111 M
b1001 -
b1001 0
b1001 5
b1001 D
b1001 I
b1001 L
b1001 P
#120
b1011 "
b1011 A
b1011 2
b1011 $
b1011 1
0<
b1011 =
b1011 E
b1011 F
16
b0 7
b0 M
b10 -
b10 0
b10 5
b10 D
b10 I
b10 L
b1010 +
b1010 .
b1010 3
b1010 B
b1010 G
b1010 K
b10 P
b1010 N
#130
b1001 $
b1001 1
b1001 2
b1001 "
b1001 A
b1001 =
b1001 E
b1001 F
b11 -
b11 0
b11 5
b11 D
b11 I
b11 L
b11 P
#140
1)
1(
1*
b10100011 "
b10100011 A
1&
1%
1'
b10100011 $
b10100011 1
b110100011 2
1?
1>
1@
b10100011 =
b10100011 E
b110100011 F
b1 -
b1 0
b1 5
b1 D
b1 I
b1 L
b10000001 ,
b10000001 /
b10000001 4
b10000001 C
b10000001 H
b100100 +
b100100 .
b100100 3
b100100 B
b100100 G
b100100 K
b1 P
b10000001 O
b100100 N
#150
1)
0(
0*
b10011100 "
b10011100 A
0%
0'
b10011100 $
b10011100 1
b0 2
0?
1<
0>
0@
b0 =
b0 E
b0 F
1;
09
b10011100 :
b10011100 J
b111 -
b111 0
b111 5
b111 D
b111 I
b111 L
b1101 ,
b1101 /
b1101 4
b1101 C
b1101 H
b1100011 +
b1100011 .
b1100011 3
b1100011 B
b1100011 G
b1100011 K
b111 P
b1101 O
b1100011 N
#160
0)
b1010011 "
b1010011 A
0&
b1010011 2
b1010011 $
b1010011 1
0<
b1010011 =
b1010011 E
b1010011 F
0;
19
b0 :
b0 J
b1 -
b1 0
b1 5
b1 D
b1 I
b1 L
b10010 ,
b10010 /
b10010 4
b10010 C
b10010 H
b1100101 +
b1100101 .
b1100101 3
b1100101 B
b1100101 G
b1100101 K
b1 P
b10010 O
b1100101 N
#170
1)
b11110010 "
b11110010 A
1&
b11110010 $
b11110010 1
b0 2
1<
b0 =
b0 E
b0 F
1;
09
b11110010 :
b11110010 J
b111 -
b111 0
b111 5
b111 D
b111 I
b111 L
b1110110 ,
b1110110 /
b1110110 4
b1110110 C
b1110110 H
b1101 +
b1101 .
b1101 3
b1101 B
b1101 G
b1101 K
b111 P
b1110110 O
b1101 N
#180
0)
b1110110 "
b1110110 A
0&
b1110110 $
b1110110 1
0;
19
b0 :
b0 J
06
b1110110 7
b1110110 M
b1001 -
b1001 0
b1001 5
b1001 D
b1001 I
b1001 L
b10001100 ,
b10001100 /
b10001100 4
b10001100 C
b10001100 H
b11101101 +
b11101101 .
b11101101 3
b11101101 B
b11101101 G
b11101101 K
b1001 P
b10001100 O
b11101101 N
#190
b11 "
b11 A
b11 $
b11 1
09
b11 :
b11 J
16
b0 7
b0 M
b110 -
b110 0
b110 5
b110 D
b110 I
b110 L
b11000101 ,
b11000101 /
b11000101 4
b11000101 C
b11000101 H
b11000110 +
b11000110 .
b11000110 3
b11000110 B
b11000110 G
b11000110 K
b110 P
b11000101 O
b11000110 N
#200
1)
b11001010 "
b11001010 A
1&
b11001010 $
b11001010 1
19
b0 :
b0 J
18
06
b11001010 7
b11001010 M
b1000 -
b1000 0
b1000 5
b1000 D
b1000 I
b1000 L
b1110111 ,
b1110111 /
b1110111 4
b1110111 C
b1110111 H
b11100101 +
b11100101 .
b11100101 3
b11100101 B
b11100101 G
b11100101 K
b1000 P
b1110111 O
b11100101 N
#210
1)
b10000010 "
b10000010 A
b10000010 $
b10000010 1
1;
09
b10000010 :
b10000010 J
08
16
b0 7
b0 M
b100 -
b100 0
b100 5
b100 D
b100 I
b100 L
b11110010 ,
b11110010 /
b11110010 4
b11110010 C
b11110010 H
b10001111 +
b10001111 .
b10001111 3
b10001111 B
b10001111 G
b10001111 K
b100 P
b11110010 O
b10001111 N
#220
1)
b11000000 "
b11000000 A
b11000000 $
b11000000 1
b11000000 :
b11000000 J
b11000101 ,
b11000101 /
b11000101 4
b11000101 C
b11000101 H
b11101000 +
b11101000 .
b11101000 3
b11101000 B
b11101000 G
b11101000 K
b11000101 O
b11101000 N
#230
1)
b10111100 "
b10111100 A
b10111100 2
b10111100 $
b10111100 1
1?
0<
b10111100 =
b10111100 E
b10111100 F
0;
19
b0 :
b0 J
b11 -
b11 0
b11 5
b11 D
b11 I
b11 L
b101101 ,
b101101 /
b101101 4
b101101 C
b101101 H
b10111101 +
b10111101 .
b10111101 3
b10111101 B
b10111101 G
b10111101 K
b11 P
b101101 O
b10111101 N
#240
0)
b1100100 "
b1100100 A
0&
b1100100 $
b1100100 1
b1100100 2
0?
b1100100 =
b1100100 E
b1100100 F
b10 -
b10 0
b10 5
b10 D
b10 I
b10 L
b1010 ,
b1010 /
b1010 4
b1010 C
b1010 H
b1100011 +
b1100011 .
b1100011 3
b1100011 B
b1100011 G
b1100011 K
b10 P
b1010 O
b1100011 N
#250
1)
b10101010 "
b10101010 A
1&
b10101010 $
b10101010 1
b0 2
1<
b0 =
b0 E
b0 F
1;
09
b10101010 :
b10101010 J
b101 -
b101 0
b101 5
b101 D
b101 I
b101 L
b10101010 ,
b10101010 /
b10101010 4
b10101010 C
b10101010 H
b100000 +
b100000 .
b100000 3
b100000 B
b100000 G
b100000 K
b101 P
b10101010 O
b100000 N
#260
1)
b10010111 "
b10010111 A
b10010111 $
b10010111 1
b10010111 :
b10010111 J
b10011 ,
b10011 /
b10011 4
b10011 C
b10011 H
b10010110 +
b10010110 .
b10010110 3
b10010110 B
b10010110 G
b10010110 K
b10011 O
b10010110 N
#270
0)
b101001 "
b101001 A
0&
b101001 $
b101001 1
0;
19
b0 :
b0 J
06
b101001 7
b101001 M
b1001 -
b1001 0
b1001 5
b1001 D
b1001 I
b1001 L
b1101011 ,
b1101011 /
b1101011 4
b1101011 C
b1101011 H
b1010011 +
b1010011 .
b1010011 3
b1010011 B
b1010011 G
b1010011 K
b1001 P
b1101011 O
b1010011 N
#280
1*
b1010100 "
b1010100 A
1'
b101010100 2
b1010100 $
b1010100 1
0<
1@
b1010100 =
b1010100 E
b101010100 F
16
b0 7
b0 M
b1 -
b1 0
b1 5
b1 D
b1 I
b1 L
b10101110 ,
b10101110 /
b10101110 4
b10101110 C
b10101110 H
b10 +
b10 .
b10 3
b10 B
b10 G
b10 K
b1 P
b10101110 O
b10 N
#290
1)
0*
b11110010 "
b11110010 A
1&
0'
b11110010 $
b11110010 1
b11110010 2
1?
0@
b11110010 =
b11110010 E
b11110010 F
b0 -
b0 0
b0 5
b0 D
b0 I
b0 L
b100011 ,
b100011 /
b100011 4
b100011 C
b100011 H
b11001111 +
b11001111 .
b11001111 3
b11001111 B
b11001111 G
b11001111 K
b0 P
b100011 O
b11001111 N
#300
1)
b11110110 "
b11110110 A
b11110110 $
b11110110 1
b0 2
0?
1<
b0 =
b0 E
b0 F
1;
09
b11110110 :
b11110110 J
b110 -
b110 0
b110 5
b110 D
b110 I
b110 L
b111100 ,
b111100 /
b111100 4
b111100 C
b111100 H
b11001010 +
b11001010 .
b11001010 3
b11001010 B
b11001010 G
b11001010 K
b110 P
b111100 O
b11001010 N
#310
0)
b10100 "
b10100 A
0&
b10100 $
b10100 1
0;
19
b0 :
b0 J
06
b10100 7
b10100 M
b1000 -
b1000 0
b1000 5
b1000 D
b1000 I
b1000 L
b1000001 ,
b1000001 /
b1000001 4
b1000001 C
b1000001 H
b10001010 +
b10001010 .
b10001010 3
b10001010 B
b10001010 G
b10001010 K
b1000 P
b1000001 O
b10001010 N
#320
1)
b10000111 "
b10000111 A
1&
b10000111 $
b10000111 1
1;
09
b10000111 :
b10000111 J
16
b0 7
b0 M
b111 -
b111 0
b111 5
b111 D
b111 I
b111 L
b10001001 ,
b10001001 /
b10001001 4
b10001001 C
b10001001 H
b1111000 +
b1111000 .
b1111000 3
b1111000 B
b1111000 G
b1111000 K
b111 P
b10001001 O
b1111000 N
#330
0)
b1110000 "
b1110000 A
0&
b1110000 $
b1110000 1
0;
b1110000 :
b1110000 J
b110 -
b110 0
b110 5
b110 D
b110 I
b110 L
b11000110 ,
b11000110 /
b11000110 4
b11000110 C
b11000110 H
b10110110 +
b10110110 .
b10110110 3
b10110110 B
b10110110 G
b10110110 K
b110 P
b11000110 O
b10110110 N
#340
b1000011 "
b1000011 A
b1000011 $
b1000011 1
b1000011 :
b1000011 J
b111 -
b111 0
b111 5
b111 D
b111 I
b111 L
b101010 ,
b101010 /
b101010 4
b101010 C
b101010 H
b10111100 +
b10111100 .
b10111100 3
b10111100 B
b10111100 G
b10111100 K
b111 P
b101010 O
b10111100 N
#350
1)
b11110101 "
b11110101 A
1&
b11110101 $
b11110101 1
1;
b11110101 :
b11110101 J
b101 -
b101 0
b101 5
b101 D
b101 I
b101 L
b10000101 ,
b10000101 /
b10000101 4
b10000101 C
b10000101 H
b1110001 +
b1110001 .
b1110001 3
b1110001 B
b1110001 G
b1110001 K
b101 P
b10000101 O
b1110001 N
#360
0)
b1 "
b1 A
0&
b1 $
b1 1
0;
b1 :
b1 J
b110 -
b110 0
b110 5
b110 D
b110 I
b110 L
b111010 ,
b111010 /
b111010 4
b111010 C
b111010 H
b111011 +
b111011 .
b111011 3
b111011 B
b111011 G
b111011 K
b110 P
b111010 O
b111011 N
#370
1*
b100100 "
b100100 A
1'
b100100100 2
b100100 $
b100100 1
0<
1@
b100100 =
b100100 E
b100100100 F
19
b0 :
b0 J
b1 -
b1 0
b1 5
b1 D
b1 I
b1 L
b11110001 ,
b11110001 /
b11110001 4
b11110001 C
b11110001 H
b10101 +
b10101 .
b10101 3
b10101 B
b10101 G
b10101 K
b1 P
b11110001 O
b10101 N
#380
0*
b110001 "
b110001 A
0'
b110001 $
b110001 1
b0 2
1<
0@
b0 =
b0 E
b0 F
06
b110001 7
b110001 M
b1001 -
b1001 0
b1001 5
b1001 D
b1001 I
b1001 L
b1001100 ,
b1001100 /
b1001100 4
b1001100 C
b1001100 H
b1100010 +
b1100010 .
b1100010 3
b1100010 B
b1100010 G
b1100010 K
b1001 P
b1001100 O
b1100010 N
#390
b1110000 "
b1110000 A
b1110000 $
b1110000 1
09
b1110000 :
b1110000 J
16
b0 7
b0 M
b111 -
b111 0
b111 5
b111 D
b111 I
b111 L
b11111000 ,
b11111000 /
b11111000 4
b11111000 C
b11111000 H
b10001111 +
b10001111 .
b10001111 3
b10001111 B
b10001111 G
b10001111 K
b111 P
b11111000 O
b10001111 N
#400
1)
b10011110 "
b10011110 A
1&
b10011110 2
b10011110 $
b10011110 1
1?
0<
b10011110 =
b10011110 E
b10011110 F
19
b0 :
b0 J
b11 -
b11 0
b11 5
b11 D
b11 I
b11 L
b1011100 ,
b1011100 /
b1011100 4
b1011100 C
b1011100 H
b10011111 +
b10011111 .
b10011111 3
b10011111 B
b10011111 G
b10011111 K
b11 P
b1011100 O
b10011111 N
#410
1)
b11000000 "
b11000000 A
b11000000 $
b11000000 1
b0 2
0?
1<
b0 =
b0 E
b0 F
1;
09
b11000000 :
b11000000 J
b110 -
b110 0
b110 5
b110 D
b110 I
b110 L
b1001001 ,
b1001001 /
b1001001 4
b1001001 C
b1001001 H
b10001001 +
b10001001 .
b10001001 3
b10001001 B
b10001001 G
b10001001 K
b110 P
b1001001 O
b10001001 N
#420
1*
0)
b101000 "
b101000 A
0&
1'
b100101000 2
b101000 $
b101000 1
0<
1@
b101000 =
b101000 E
b100101000 F
0;
19
b0 :
b0 J
b0 -
b0 0
b0 5
b0 D
b0 I
b0 L
b1010001 ,
b1010001 /
b1010001 4
b1010001 C
b1010001 H
b11010111 +
b11010111 .
b11010111 3
b11010111 B
b11010111 G
b11010111 K
b0 P
b1010001 O
b11010111 N
#430
1!
0*
b0 "
b0 A
1#
0'
b0 $
b0 1
b0 2
1<
0@
b0 =
b0 E
b0 F
b100 -
b100 0
b100 5
b100 D
b100 I
b100 L
b11000010 ,
b11000010 /
b11000010 4
b11000010 C
b11000010 H
b1100 +
b1100 .
b1100 3
b1100 B
b1100 G
b1100 K
b100 P
b11000010 O
b1100 N
#440
1)
b11101110 "
b11101110 A
0!
1&
0#
b11101110 $
b11101110 1
18
06
b11101110 7
b11101110 M
b1000 -
b1000 0
b1000 5
b1000 D
b1000 I
b1000 L
b111101 ,
b111101 /
b111101 4
b111101 C
b111101 H
b1110111 +
b1110111 .
b1110111 3
b1110111 B
b1110111 G
b1110111 K
b1000 P
b111101 O
b1110111 N
#450
0)
b1111101 "
b1111101 A
0&
b1111101 2
b1111101 $
b1111101 1
0<
b1111101 =
b1111101 E
b1111101 F
08
16
b0 7
b0 M
b11 -
b11 0
b11 5
b11 D
b11 I
b11 L
b1101101 ,
b1101101 /
b1101101 4
b1101101 C
b1101101 H
b1111110 +
b1111110 .
b1111110 3
b1111110 B
b1111110 G
b1111110 K
b11 P
b1101101 O
b1111110 N
#460
b11110 "
b11110 A
b11110 $
b11110 1
b11110 2
b11110 =
b11110 E
b11110 F
b11010011 ,
b11010011 /
b11010011 4
b11010011 C
b11010011 H
b11111 +
b11111 .
b11111 3
b11111 B
b11111 G
b11111 K
b11010011 O
b11111 N
#470
b1110111 "
b1110111 A
b1110111 $
b1110111 1
b1110111 2
b1110111 =
b1110111 E
b1110111 F
b1011011 ,
b1011011 /
b1011011 4
b1011011 C
b1011011 H
b1111000 +
b1111000 .
b1111000 3
b1111000 B
b1111000 G
b1111000 K
b1011011 O
b1111000 N
#480
b1000000 "
b1000000 A
b1000000 $
b1000000 1
b1000000 2
b1000000 =
b1000000 E
b1000000 F
b10 -
b10 0
b10 5
b10 D
b10 I
b10 L
b101010 ,
b101010 /
b101010 4
b101010 C
b101010 H
b111111 +
b111111 .
b111111 3
b111111 B
b111111 G
b111111 K
b10 P
b101010 O
b111111 N
#490
1(
1*
b10100 "
b10100 A
1%
1'
b10100 $
b10100 1
b100010100 2
1>
1@
b10100 =
b10100 E
b100010100 F
b0 -
b0 0
b0 5
b0 D
b0 I
b0 L
b10001110 ,
b10001110 /
b10001110 4
b10001110 C
b10001110 H
b10000110 +
b10000110 .
b10000110 3
b10000110 B
b10000110 G
b10000110 K
b0 P
b10001110 O
b10000110 N
#500
1)
0(
0*
b11111110 "
b11111110 A
1&
0%
0'
b11111110 $
b11111110 1
b0 2
1<
0>
0@
b0 =
b0 E
b0 F
1;
09
b11111110 :
b11111110 J
b101 -
b101 0
b101 5
b101 D
b101 I
b101 L
b100110 ,
b100110 /
b100110 4
b100110 C
b100110 H
b11111010 +
b11111010 .
b11111010 3
b11111010 B
b11111010 G
b11111010 K
b101 P
b100110 O
b11111010 N
#510
1(
0)
b1110100 "
b1110100 A
0&
1%
b1110100 2
b1110100 $
b1110100 1
0<
1>
b1110100 =
b1110100 E
b1110100 F
0;
19
b0 :
b0 J
b1 -
b1 0
b1 5
b1 D
b1 I
b1 L
b101111 ,
b101111 /
b101111 4
b101111 C
b101111 H
b10100011 +
b10100011 .
b10100011 3
b10100011 B
b10100011 G
b10100011 K
b1 P
b101111 O
b10100011 N
#520
0(
b11011 "
b11011 A
0%
b11011 $
b11011 1
b11011 2
0>
b11011 =
b11011 E
b11011 F
b1000100 ,
b1000100 /
b1000100 4
b1000100 C
b1000100 H
b1011111 +
b1011111 .
b1011111 3
b1011111 B
b1011111 G
b1011111 K
b1000100 O
b1011111 N
#530
1)
b11000010 "
b11000010 A
1&
b11000010 $
b11000010 1
b0 2
1<
b0 =
b0 E
b0 F
1;
09
b11000010 :
b11000010 J
b100 -
b100 0
b100 5
b100 D
b100 I
b100 L
b11100110 ,
b11100110 /
b11100110 4
b11100110 C
b11100110 H
b11001011 +
b11001011 .
b11001011 3
b11001011 B
b11001011 G
b11001011 K
b100 P
b11100110 O
b11001011 N
#540
1*
0)
b10110 "
b10110 A
0&
1'
b100010110 2
b10110 $
b10110 1
0<
1@
b10110 =
b10110 E
b100010110 F
0;
19
b0 :
b0 J
b0 -
b0 0
b0 5
b0 D
b0 I
b0 L
b11101101 ,
b11101101 /
b11101101 4
b11101101 C
b11101101 H
b101001 +
b101001 .
b101001 3
b101001 B
b101001 G
b101001 K
b0 P
b11101101 O
b101001 N
